morpheus/__init__.py
morpheus/__main__.py
morpheus/__version__.py
morpheus/classifier.py
morpheus/core/__init__.py
morpheus/core/base_model.py
morpheus/core/helpers.py
morpheus/core/hparams.py
morpheus/core/model.py
morpheus/core/model_config.json
morpheus/core/unet.py
morpheus/core/model_weights/checkpoint
morpheus/core/model_weights/model-440.data-00000-of-00001
morpheus/core/model_weights/model-440.index
morpheus/core/model_weights/model-440.meta
morpheus/data/__init__.py
morpheus/data/example.py
morpheus_astro-0.5.1.dist-info/LICENSE
morpheus_astro-0.5.1.dist-info/METADATA
morpheus_astro-0.5.1.dist-info/WHEEL
morpheus_astro-0.5.1.dist-info/entry_points.txt
morpheus_astro-0.5.1.dist-info/top_level.txt
morpheus_astro-0.5.1.dist-info/RECORD
