Metadata-Version: 2.1
Name: morpheus-astro
Version: 0.5.1
Summary: A Library For Generating Morphological Semantic Segmentation Maps of Astronomical Images
Home-page: https://github.com/morpheus-project/morpheus
Author: Ryan Hausen & Brant Robertson
Author-email: rhausen@ucsc.edu
License: MIT
Platform: UNKNOWN
Classifier: Programming Language :: Python
Classifier: Programming Language :: Python :: 3
Classifier: Programming Language :: Python :: 3.6
Classifier: Programming Language :: Python :: Implementation :: PyPy
Classifier: License :: OSI Approved :: MIT License
Classifier: Intended Audience :: Science/Research
Classifier: Development Status :: 4 - Beta
Classifier: Operating System :: POSIX :: Linux
Classifier: Topic :: Scientific/Engineering
Requires-Python: >=3.6
Requires-Dist: numpy
Requires-Dist: colorama
Requires-Dist: astropy
Requires-Dist: tqdm
Requires-Dist: matplotlib
Requires-Dist: imageio
Requires-Dist: scikit-image
Requires-Dist: scipy
